NeuralNetworkPY/__init__.py
NeuralNetworkPY-0.0.2.dist-info/LICENSE.txt
NeuralNetworkPY-0.0.2.dist-info/METADATA
NeuralNetworkPY-0.0.2.dist-info/WHEEL
NeuralNetworkPY-0.0.2.dist-info/top_level.txt
NeuralNetworkPY-0.0.2.dist-info/RECORD
