Metadata-Version: 2.1
Name: NeuralNetworkPY
Version: 0.0.2
Summary: An easy-to-use Neural Network library I'm building from scratch.
Home-page: https://github.com/And1210/NeuralNetworkPY
Author: Andrew Farley
Author-email: amf7crazy@gmail.com
License: UNKNOWN
Platform: UNKNOWN
Classifier: Programming Language :: Python :: 3
Classifier: License :: OSI Approved :: MIT License
Classifier: Operating System :: OS Independent
